{
  "file": "./models/readings.json",
  "readings": [
    {
      "timeStamp": "30/07/2023, 23:36:16",
      "code": 300,
      "temperature": 15.14,
      "windSpeed": 4.47,
      "windDirection": 234,
      "pressure": 1004,
      "_id": "77e1d26a-1a71-4e92-a9ec-bfdd98a1498a",
      "stationid": "95670ce3-786c-4a65-9319-16c7e2da2b01"
    },
    {
      "timeStamp": "30/07/2023, 23:36:56",
      "code": 231,
      "temperature": 12,
      "windSpeed": 12,
      "windDirection": 12,
      "pressure": 12,
      "_id": "66abe398-7b12-43c9-8aa9-4d0cb9758f34",
      "stationid": "95670ce3-786c-4a65-9319-16c7e2da2b01"
    },
    {
      "timeStamp": "30/07/2023, 23:37:15",
      "code": 232,
      "temperature": 12,
      "windSpeed": 12,
      "windDirection": 12,
      "pressure": 12,
      "_id": "5993511b-47ea-4c18-a10b-37a71dc5c7ca",
      "stationid": "95670ce3-786c-4a65-9319-16c7e2da2b01"
    },
    {
      "timeStamp": "30/07/2023, 23:42:28",
      "code": 302,
      "temperature": 23,
      "windSpeed": 23,
      "windDirection": 23,
      "pressure": 23,
      "_id": "ae180c9d-e73e-4dbb-b70c-64ee51900d83",
      "stationid": "95670ce3-786c-4a65-9319-16c7e2da2b01"
    },
    {
      "timeStamp": "30/07/2023, 23:42:39",
      "code": 800,
      "temperature": 34,
      "windSpeed": 34,
      "windDirection": 34,
      "pressure": 34,
      "_id": "356fbd97-cb74-43ec-8b2e-7124d6362166",
      "stationid": "95670ce3-786c-4a65-9319-16c7e2da2b01"
    },
    {
      "timeStamp": "30/07/2023, 23:43:50",
      "code": 800,
      "temperature": 23,
      "windSpeed": 23,
      "windDirection": 23,
      "pressure": 23,
      "_id": "e4913180-e3ea-49c7-8fd4-159e686ce4a5",
      "stationid": "95670ce3-786c-4a65-9319-16c7e2da2b01"
    }
  ]
}